{"ID":100019,"Key":"0f02da9d67765ad7e91bbb30dfee7e17bb4b7ce6bdb75e302e0ea54bc22e3416","Raw":"250227094949234081000501007251","Audit":{"CreatedAt":"2025-02-27T09:49:49.234094Z","CreatedBy":"sys_service","CreatedOn":"orion","CreatedAtDisplay":"2025-02-27 09:49:49","Updates":[{"UpdatedAt":"2025-02-27T09:49:49.234094Z","UpdateAction":"CREA","UpdatedBy":"sys_service","UpdatedOn":"orion","UpdatedAtDisplay":"2025-02-27 09:49:49","UpdateNotes":"New Template created 6973"},{"UpdatedAt":"2025-02-27T09:52:24.352201Z","UpdateAction":"DELE","UpdatedBy":"sys_service","UpdatedOn":"orion","UpdatedAtDisplay":"2025-02-27 09:52:24","UpdateNotes":"Clearing Template 100019 @ initialisation "}],"DeletedAt":"2025-02-27T09:52:24.352201Z","DeletedBy":"sys_service","DeletedOn":"orion","DeletedAtDisplay":"2025-02-27 09:52:24","AuditSequence":2,"DBVersion":1},"Field1":6973,"Field2":"Test 6973","Field3":"2025-02-27T10:09:49.234093Z"}